acenav_api/__init__.py
acenav_api/command_builder.py
acenav_api/field_parser.py
acenav_api/j1939_packet_parser.py
acenav_api/message_protocol.py
acenav_api/package.py
acenav_api/packet_parser.py
acenav_api/utils.py
acenav_api/configs/INS502-next.json
acenav_api/configs/INS502.json
acenav_api/configs/MTLT335D.json
acenav_api-1.0.16.dist-info/METADATA
acenav_api-1.0.16.dist-info/WHEEL
acenav_api-1.0.16.dist-info/top_level.txt
acenav_api-1.0.16.dist-info/RECORD
