Metadata-Version: 2.1
Name: acenav-api
Version: 1.0.16
Summary: Aceinna Navigation System API
Home-page: https://github.com/Aceinna
Author: Aceinna, Inc
Author-email: info@aceinna.com
License: Apache 2.0
Platform: UNKNOWN
Requires-Python: >=2.7, !=3.0.*, !=3.1.*
